doctor_leipzig/__init__.py
doctor_leipzig/doctor_leipzig.py
doctor_leipzig-2.0.dist-info/METADATA
doctor_leipzig-2.0.dist-info/WHEEL
doctor_leipzig-2.0.dist-info/top_level.txt
doctor_leipzig-2.0.dist-info/RECORD
