Metadata-Version: 2.1
Name: doctor-leipzig
Version: 2.0
Summary: Interlinear (Leipzig Rules) glossing for Markdown
Home-page: https://github.com/parryc/doctor_leipzig
Author: parryc
Author-email: parry@parryc.com
License: MIT
Keywords: interlinear leipzig glossing gloss markdown
Platform: UNKNOWN
Classifier: Intended Audience :: Developers
Classifier: Programming Language :: Python
Classifier: Topic :: Software Development :: Libraries :: Python Modules
Classifier: Topic :: Text Processing :: Filters
Classifier: Topic :: Text Processing :: Markup :: HTML
Requires-Dist: markdown (>=3.3.3)
